{
  "game_id": 2,
  "turn": 33,
  "screenshot": "data/raw/game_2/turn_033.png",
  "current_player": 0,
  "player_names": {
    "0": "red",
    "1": "blue"
  },
  "scores": {
    "red": 6,
    "blue": 4
  },
  "board_state": {
    "grid_size": 4,
    "horizontal_lines": [
      [
        1,
        1,
        1,
        1
      ],
      [
        1,
        1,
        1,
        1
      ],
      [
        1,
        1,
        1,
        1
      ],
      [
        1,
        1,
        0,
        1
      ],
      [
        0,
        0,
        1,
        1
      ]
    ],
    "vertical_lines": [
      [
        0,
        1,
        1,
        1,
        1
      ],
      [
        1,
        1,
        1,
        1,
        1
      ],
      [
        1,
        1,
        1,
        0,
        0
      ],
      [
        0,
        1,
        0,
        1,
        1
      ]
    ],
    "box_owners": [
      [
        null,
        0,
        1,
        1
      ],
      [
        1,
        0,
        0,
        0
      ],
      [
        0,
        0,
        null,
        null
      ],
      [
        null,
        null,
        null,
        1
      ]
    ]
  },
  "move_info": {
    "available_moves": [
      [
        "h",
        3,
        2
      ],
      [
        "h",
        4,
        0
      ],
      [
        "h",
        4,
        1
      ],
      [
        "v",
        0,
        0
      ],
      [
        "v",
        2,
        3
      ],
      [
        "v",
        2,
        4
      ],
      [
        "v",
        3,
        0
      ],
      [
        "v",
        3,
        2
      ]
    ],
    "total_possible_moves": 40,
    "moves_made": 32,
    "remaining_moves": 8
  },
  "move_taken": [
    "v",
    0,
    1
  ],
  "move_player": 0,
  "strategy_info": {
    "completed_boxes_this_turn": true,
    "potential_boxes": {
      "boxes_with_2_edges": 5,
      "boxes_with_3_edges": 1,
      "total_potential_boxes": 6
    },
    "game_phase": "late",
    "score_difference": 2,
    "is_winning": true
  },
  "result": {
    "game_completed": false,
    "final_scores": null,
    "winner": null
  }
}