{
  "game_id": 48,
  "turn": 39,
  "screenshot": "data/raw/game_48/turn_039.png",
  "current_player": 1,
  "player_names": {
    "0": "red",
    "1": "blue"
  },
  "scores": {
    "red": 8,
    "blue": 6
  },
  "board_state": {
    "grid_size": 4,
    "horizontal_lines": [
      [
        1,
        0,
        1,
        1
      ],
      [
        1,
        1,
        1,
        1
      ],
      [
        1,
        1,
        1,
        1
      ],
      [
        1,
        1,
        1,
        1
      ],
      [
        1,
        1,
        1,
        1
      ]
    ],
    "vertical_lines": [
      [
        1,
        1,
        0,
        1,
        1
      ],
      [
        1,
        1,
        1,
        1,
        1
      ],
      [
        1,
        1,
        1,
        1,
        1
      ],
      [
        1,
        1,
        1,
        1,
        1
      ]
    ],
    "box_owners": [
      [
        1,
        null,
        null,
        0
      ],
      [
        1,
        1,
        1,
        0
      ],
      [
        1,
        0,
        0,
        0
      ],
      [
        1,
        0,
        0,
        0
      ]
    ]
  },
  "move_info": {
    "available_moves": [
      [
        "h",
        0,
        1
      ],
      [
        "v",
        0,
        2
      ]
    ],
    "total_possible_moves": 40,
    "moves_made": 38,
    "remaining_moves": 2
  },
  "move_taken": [
    "h",
    1,
    2
  ],
  "strategy_info": {
    "completed_boxes_this_turn": false,
    "potential_boxes": {
      "boxes_with_3_edges": 1,
      "total_potential_boxes": 1
    },
    "game_phase": "late",
    "score_difference": 2,
    "is_winning": false
  },
  "result": {
    "game_completed": false,
    "final_scores": null,
    "winner": null
  }
}